MANIFEST.in
README.md
setup.py
python_sentiment.egg-info/PKG-INFO
python_sentiment.egg-info/SOURCES.txt
python_sentiment.egg-info/dependency_links.txt
python_sentiment.egg-info/entry_points.txt
python_sentiment.egg-info/requires.txt
python_sentiment.egg-info/top_level.txt
sentiment/MNB_clf.pickle
sentiment/all_words.pickle
sentiment/documents.pickle
sentiment/sentiment.py