Metadata-Version: 2.1
Name: python-sentiment
Version: 1.1.0
Summary: A python package to do sentiment analysis of a string
Home-page: UNKNOWN
Author: Sahil Ahuja
Author-email: sahil27ahuja1999@gmail.com
License: MIT
Platform: UNKNOWN
Classifier: Development Status :: 3 - Alpha
Classifier: Intended Audience :: Developers
Classifier: Topic :: Software Development :: Build Tools
Classifier: License :: OSI Approved :: MIT License
Classifier: Programming Language :: Python :: 3
Classifier: Programming Language :: Python :: 3.4
Classifier: Programming Language :: Python :: 3.5
Classifier: Programming Language :: Python :: 3.6
